{
    "version": "2026.4.0-25745196355",
    "architecture": {
        "64bit": {
            "url": "https://github.com/kodexa-ai/kdx-cli-releases/releases/download/v2026.4.0-25745196355/kdx_2026.4.0-25745196355_windows_x86_64.zip",
            "bin": [
                "kdx.exe"
            ],
            "hash": "f640a6076f8229347bc331caedc041cfa566100114b0b075f34770df2923990b"
        }
    },
    "homepage": "https://www.kodexa.com",
    "license": "Proprietary",
    "description": "Kodexa CLI - Command-line interface for Kodexa platform"
}